toto_logger/__init__.py
toto_logger/logger.py
toto_logger/toto_logger.py
toto_logger_nicolasances-1.0.5.dist-info/LICENSE
toto_logger_nicolasances-1.0.5.dist-info/METADATA
toto_logger_nicolasances-1.0.5.dist-info/WHEEL
toto_logger_nicolasances-1.0.5.dist-info/top_level.txt
toto_logger_nicolasances-1.0.5.dist-info/RECORD
