Metadata-Version: 2.1
Name: toto-logger-nicolasances
Version: 1.0.5
Summary: A simple logger for Toto
Home-page: https://github.com/nicolasances/py-toto-logger
Author: nicolasances
Author-email: nicolas.matteazzi@gmail.com
License: UNKNOWN
Platform: UNKNOWN
Classifier: Programming Language :: Python :: 3
Classifier: License :: OSI Approved :: MIT License
Classifier: Operating System :: OS Independent
Requires-Python: >=3.6
